[
	{
		"name": "Maglemosia",
		"leaderName": "Anundr",
		"adjective": ["Ancient Scandanavian"],
		"startBias": ["Snow"],
		"preferredVictoryType": "Diplomatic",
		
		"startIntroPart1": "Hejsan",
		"startIntroPart2": "Good Hunting my Friend!",
		
		"declaringWar": "My enemies tremble like a leaf in the wind.",
		"attacked": "Challenge Accepted!",
		"defeated": "Ancestors, take us to the great hunt.",
		"introduction": "May the rivers run clear, the forests stand tall, and the fish be plentiful in your path.",
		
		"neutralHello": "Greetings.",
		"neutralLetsHearIt": ["Go on.","What news?","Speak."],
		"neutralNo": ["Never.","No!","I refuse."],
		"neutralYes": ["Very well.","Of course, yes.","That is very good."],

		"hateHello": "What do you want now?",
		"hateLetsHearIt": ["Speak!","What do you say?","Go on."],
		"hateNo": ["That is not possible!","We are not agreeing to that!","I beg your pardon?"],
		"hateYes": ["That is fine.","That is good enough.","Very well..."],
		
		"afterPeace": "A sensinble decision.",
		"tradeRequest": "It would be unwise to refuse.",

		"outerColor": [141,11,100],
		"innerColor": [152,245,249],
		"uniqueName": "Hearth",
		"unique": ["[+2 Faith] from every [Snow]"],
		"cities": ["Álǫf's Glenn","House of Félagi","The Encampment","Hreiðarr's Hunt"]
	}
]
